btrc.py
setup.py
btrc.egg-info/PKG-INFO
btrc.egg-info/SOURCES.txt
btrc.egg-info/dependency_links.txt
btrc.egg-info/entry_points.txt
btrc.egg-info/requires.txt
btrc.egg-info/top_level.txt