Metadata-Version: 1.1
Name: btrc
Version: 3.2.0
Summary: Couchbase view stats collector
Home-page: UNKNOWN
Author: Pavel Paulau
Author-email: pavel.paulau@gmail.com
License: UNKNOWN
Platform: UNKNOWN
Classifier: Programming Language :: Python
Classifier: Programming Language :: Python :: 2.6
Classifier: Development Status :: 5 - Production/Stable
Classifier: Environment :: Other Environment
Classifier: Intended Audience :: Developers
Classifier: License :: OSI Approved :: Apache Software License
Classifier: Operating System :: OS Independent
Classifier: Topic :: Software Development :: Libraries :: Python Modules
